pybud/__init__.py
pybud/_drawer.cpython-310-darwin.so
pybud/session.py
pybud/window.py
pybud/callbacks/__init__.py
pybud/callbacks/window.py
pybud/callbacks/widgets/__init__.py
pybud/callbacks/widgets/combobox.py
pybud/callbacks/widgets/multiplechoice.py
pybud/datatypes/__init__.py
pybud/datatypes/color.py
pybud/datatypes/point.py
pybud/datatypes/position.py
pybud/datatypes/size.py
pybud/drawer/__init__.py
pybud/drawer/__init__.pyi
pybud/drawer/ansi.py
pybud/drawer/ansi.pyi
pybud/drawer/color.py
pybud/drawer/color.pyi
pybud/enums/__init__.py
pybud/enums/window/window_closing_reason.py
pybud/mixins/__init__.py
pybud/mixins/callbackmixin.py
pybud/mixins/depthmixin.py
pybud/widgets/__init__.py
pybud/widgets/combobox.py
pybud/widgets/label.py
pybud/widgets/multiplechoice.py
pybud/widgets/textbox.py
pybud/widgets/widget.py
pybud_gui-3.1.0.dist-info/METADATA
pybud_gui-3.1.0.dist-info/WHEEL
pybud_gui-3.1.0.dist-info/top_level.txt
pybud_gui-3.1.0.dist-info/RECORD
