Metadata-Version: 2.2
Name: pybud-gui
Version: 3.1.0
Summary: A library for creating GUIs in console, with a Rust backend, with tons of different modules, such as `Session`, `Window`s, `Widget`s, and many more!
Author-email: Amirali Mollaei <me.amiralimollaei@gmail.com>
License: BSD 4-clause License
Classifier: Operating System :: Microsoft :: Windows
Classifier: Operating System :: POSIX :: Linux
Classifier: Operating System :: MacOS
Classifier: Programming Language :: Python :: 3
Classifier: Programming Language :: Rust
Classifier: Programming Language :: Python :: Implementation :: CPython
Classifier: Programming Language :: Python :: Implementation :: PyPy
Requires-Python: >=3.10
Requires-Dist: readchar
